bceserver/__init__.py
bceserver/auth/__init__.py
bceserver/auth/auth.py
bceserver/auth/consts.py
bceserver/auth/fake.py
bceserver/auth/plugins.py
bceserver/conf/__init__.py
bceserver/conf/conf.py
bceserver/constants/__init__.py
bceserver/constants/constants.py
bceserver/context/__init__.py
bceserver/context/context.py
bceserver/context/singleton_context.py
bceserver/db/__init__.py
bceserver/db/config.py
bceserver/db/db.py
bceserver/db/mongodb/__init__.py
bceserver/db/mongodb/config.py
bceserver/db/mongodb/mongodb.py
bceserver/errors/__init__.py
bceserver/errors/errors.py
bceserver/middleware/__init__.py
bceserver/middleware/impersonate.py
bceserver/middleware/response.py
bceserver/naming/__init__.py
bceserver/naming/naming.py
bceserver-1.0.8.dist-info/METADATA
bceserver-1.0.8.dist-info/WHEEL
bceserver-1.0.8.dist-info/top_level.txt
bceserver-1.0.8.dist-info/RECORD
