Metadata-Version: 2.1
Name: bceserver
Version: 1.0.8
Summary: server-go in python
Home-page: https://console.cloud.baidu-int.com/devops/icode/repos/baidu/themis/server-python/tree/master
Author: zhoubohan
Author-email: zhoubohan.pro@gmail.com
License: MIT
Classifier: Programming Language :: Python
Classifier: Programming Language :: Python :: 3
Classifier: Programming Language :: Python :: 3.9
Classifier: Programming Language :: Python :: 3.10
Classifier: Programming Language :: Python :: 3.11
Requires-Python: >=3.9
Requires-Dist: bce-python-sdk==0.8.87
Requires-Dist: bceidaas==0.0.1.dev2
Requires-Dist: bce-internal-sdk
Requires-Dist: bcelogger
Requires-Dist: pydantic
Requires-Dist: fastapi
Requires-Dist: pypinyin
Requires-Dist: tenantv1
Requires-Dist: toml
